[
  {
    "id": 1,
    "type": "emoji_scale",
    "text": "お客様からの感謝や、チームからの「ありがとう」が、日々の喜びにつながっていると感じますか？",
    "options": [
      { "value": 1, "text": "全く思わない" },
      { "value": 2, "text": "あまり思わない" },
      { "value": 3, "text": "どちらとも言えない" },
      { "value": 4, "text": "そう思う" },
      { "value": 5, "text": "強くそう思う" }
    ]
  },
  {
    "id": 2,
    "type": "emoji_scale",
    "text": "あなたの良い仕事や努力が、チームや会社にきちんと認められていると感じますか？",
    "options": [
      { "value": 1, "text": "全く思わない" },
      { "value": 2, "text": "あまり思わない" },
      { "value": 3, "text": "どちらとも言えない" },
      { "value": 4, "text": "そう思う" },
      { "value": 5, "text": "強くそう思う" }
    ]
  },
  {
    "id": 3,
    "type": "emoji_scale",
    "text": "仕事を通じて得た学びや経験が、あなたのブライダルプランナーとしての成長を後押ししていると感じますか？",
    "options": [
      { "value": 1, "text": "全く思わない" },
      { "value": 2, "text": "あまり思わない" },
      { "value": 3, "text": "どちらとも言えない" },
      { "value": 4, "text": "そう思う" },
      { "value": 5, "text": "強くそう思う" }
    ]
  },
  {
    "id": 4,
    "type": "emoji_scale",
    "text": "チームの中で、お互いの良い点や貢献を伝え合う文化があると感じますか？",
    "options": [
      { "value": 1, "text": "全く思わない" },
      { "value": 2, "text": "あまり思わない" },
      { "value": 3, "text": "どちらとも言えない" },
      { "value": 4, "text": "そう思う" },
      { "value": 5, "text": "強くそう思う" }
    ]
  },
  {
    "id": 5,
    "type": "emoji_scale",
    "text": "お客様のために「こうしたい」というあなたのアイデアや提案が、チームで尊重され、実現できる機会がありますか？",
    "options": [
      { "value": 1, "text": "全く思わない" },
      { "value": 2, "text": "あまり思わない" },
      { "value": 3, "text": "どちらとも言えない" },
      { "value": 4, "text": "そう思う" },
      { "value": 5, "text": "強くそう思う" }
    ]
  },
  {
    "id": 6,
    "type": "emoji_scale",
    "text": "仕事の進め方について、あなたの工夫や裁量が活かされていると感じますか？",
    "options": [
      { "value": 1, "text": "全く思わない" },
      { "value": 2, "text": "あまり思わない" },
      { "value": 3, "text": "どちらとも言えない" },
      { "value": 4, "text": "そう思う" },
      { "value": 5, "text": "強くそう思う" }
    ]
  },
  {
    "id": 7,
    "type": "emoji_scale",
    "text": "もっとお客様に喜んでいただくために、自ら行動を起こせる自由度があると感じますか？",
    "options": [
      { "value": 1, "text": "全く思わない" },
      { "value": 2, "text": "あまり思わない" },
      { "value": 3, "text": "どちらとも言えない" },
      { "value": 4, "text": "そう思う" },
      { "value": 5, "text": "強くそう思う" }
    ]
  },
  {
    "id": 8,
    "type": "emoji_scale",
    "text": "お客様に最高の笑顔を届けるために、自分の心身の健康を大切にできていますか？（例：十分な睡眠、リフレッシュする時間など）",
    "options": [
      { "value": 1, "text": "全く思わない" },
      { "value": 2, "text": "あまり思わない" },
      { "value": 3, "text": "どちらとも言えない" },
      { "value": 4, "text": "そう思う" },
      { "value": 5, "text": "強くそう思う" }
    ]
  },
  {
    "id": 9,
    "type": "emoji_scale",
    "text": "仕事とプライベートのバランスが取れており、充実した毎日を送れていると感じますか？",
    "options": [
      { "value": 1, "text": "全く思わない" },
      { "value": 2, "text": "あまり思わない" },
      { "value": 3, "text": "どちらとも言えない" },
      { "value": 4, "text": "そう思う" },
      { "value": 5, "text": "強くそう思う" }
    ]
  },
  {
    "id": 10,
    "type": "emoji_scale",
    "text": "もしストレスを感じた時、会社やチームに安心して相談できる環境がありますか？",
    "options": [
      { "value": 1, "text": "全く思わない" },
      { "value": 2, "text": "あまり思わない" },
      { "value": 3, "text": "どちらとも言えない" },
      { "value": 4, "text": "そう思う" },
      { "value": 5, "text": "強くそう思う" }
    ]
  },
  {
    "id": 11,
    "type": "emoji_scale",
    "text": "お客様の幸せを願うように、あなた自身の幸せも大切にできていますか？",
    "options": [
      { "value": 1, "text": "全く思わない" },
      { "value": 2, "text": "あまり思わない" },
      { "value": 3, "text": "どちらとも言えない" },
      { "value": 4, "text": "そう思う" },
      { "value": 5, "text": "強くそう思う" }
    ]
  },
  {
    "id": 12,
    "type": "emoji_scale",
    "text": "チームの仲間は、困った時に助け合い、支え合える存在だと感じますか？",
    "options": [
      { "value": 1, "text": "全く思わない" },
      { "value": 2, "text": "あまり思わない" },
      { "value": 3, "text": "どちらとも言えない" },
      { "value": 4, "text": "そう思う" },
      { "value": 5, "text": "強くそう思う" }
    ]
  },
  {
    "id": 13,
    "type": "emoji_scale",
    "text": "「CRAZYらしい結婚式」を創るという共通の目標に向かって、チーム一丸となって取り組めていると感じますか？",
    "options": [
      { "value": 1, "text": "全く思わない" },
      { "value": 2, "text": "あまり思わない" },
      { "value": 3, "text": "どちらとも言えない" },
      { "value": 4, "text": "そう思う" },
      { "value": 5, "text": "強くそう思う" }
    ]
  },
  {
    "id": 14,
    "type": "emoji_scale",
    "text": "チームの中で、あなたの個性や強みが活かされていると感じますか？",
    "options": [
      { "value": 1, "text": "全く思わない" },
      { "value": 2, "text": "あまり思わない" },
      { "value": 3, "text": "どちらとも言えない" },
      { "value": 4, "text": "そう思う" },
      { "value": 5, "text": "強くそう思う" }
    ]
  },
  {
    "id": 15,
    "type": "emoji_scale",
    "text": "チームの中で、互いを尊敬し、信頼し合える関係が築けていると感じますか？",
    "options": [
      { "value": 1, "text": "全く思わない" },
      { "value": 2, "text": "あまり思わない" },
      { "value": 3, "text": "どちらとも言えない" },
      { "value": 4, "text": "そう思う" },
      { "value": 5, "text": "強くそう思う" }
    ]
  },
  {
    "id": 16,
    "type": "emoji_scale",
    "text": "CRAZYが目指す「結婚式の、その先にある、人生の豊かさ」というビジョンに共感し、日々の仕事の原動力になっていますか？",
    "options": [
      { "value": 1, "text": "全く思わない" },
      { "value": 2, "text": "あまり思わない" },
      { "value": 3, "text": "どちらとも言えない" },
      { "value": 4, "text": "そう思う" },
      { "value": 5, "text": "強くそう思う" }
    ]
  },
  {
    "id": 17,
    "type": "emoji_scale",
    "text": "あなたの仕事が、CRAZYの目指す未来にどう貢献しているか、明確に理解していますか？",
    "options": [
      { "value": 1, "text": "全く思わない" },
      { "value": 2, "text": "あまり思わない" },
      { "value": 3, "text": "どちらとも言えない" },
      { "value": 4, "text": "そう思う" },
      { "value": 5, "text": "強くそう思う" }
    ]
  },
  {
    "id": 18,
    "type": "emoji_scale",
    "text": "CRAZYの文化や価値観が、あなたの仕事や生き方にフィットしていると感じますか？",
    "options": [
      { "value": 1, "text": "全く思わない" },
      { "value": 2, "text": "あまり思わない" },
      { "value": 3, "text": "どちらとも言えない" },
      { "value": 4, "text": "そう思う" },
      { "value": 5, "text": "強くそう思う" }
    ]
  },
  {
    "id": 19,
    "type": "emoji_scale",
    "text": "あなたの仕事の目標は明確で、達成に向けてワクワクする気持ちがありますか？",
    "options": [
      { "value": 1, "text": "全く思わない" },
      { "value": 2, "text": "あまり思わない" },
      { "value": 3, "text": "どちらとも言えない" },
      { "value": 4, "text": "そう思う" },
      { "value": 5, "text": "強くそう思う" }
    ]
  },
  {
    "id": 20,
    "type": "emoji_scale",
    "text": "目標達成のために、会社やチームから必要なサポートや情報が得られていると感じますか？",
    "options": [
      { "value": 1, "text": "全く思わない" },
      { "value": 2, "text": "あまり思わない" },
      { "value": 3, "text": "どちらとも言えない" },
      { "value": 4, "text": "そう思う" },
      { "value": 5, "text": "強くそう思う" }
    ]
  },
  {
    "id": 21,
    "type": "emoji_scale",
    "text": "定期的に、あなたのキャリアや成長について、上長や会社と対話する機会がありますか？",
    "options": [
      { "value": 1, "text": "全く思わない" },
      { "value": 2, "text": "あまり思わない" },
      { "value": 3, "text": "どちらとも言えない" },
      { "value": 4, "text": "そう思う" },
      { "value": 5, "text": "強くそう思う" }
    ]
  },
  {
    "id": 22,
    "type": "emoji_scale",
    "text": "あなたはCRAZYを友人や知人に自信を持って勧めたいと思いますか？",
    "options": [
      { "value": 1, "text": "全く思わない" },
      { "value": 2, "text": "あまり思わない" },
      { "value": 3, "text": "どちらとも言えない" },
      { "value": 4, "text": "そう思う" },
      { "value": 5, "text": "強くそう思う" }
    ]
  },
  {
    "id": 23,
    "type": "text_input",
    "text": "「もっとお客様に喜んでいただくために、自分にできること」という視点で、自身のスキルアップや成長について考えていますか？",
    "placeholder": "あなたの考えや目標を自由にお聞かせください..."
  },
  {
    "id": 24,
    "type": "text_input",
    "text": "「もっとCRAZYを良くするために」という視点で、あなた自身が貢献できることは何だと思いますか？",
    "placeholder": "あなたのアイデアや提案を自由にお聞かせください..."
  },
  {
    "id": 25,
    "type": "text_input",
    "text": "CRAZYで働く中で、あなたが最も大切にしていることや、やりがいを感じる瞬間はどんな時ですか？",
    "placeholder": "具体的なエピソードや想いを自由にお聞かせください..."
  },
  {
    "id": 26,
    "type": "text_input",
    "text": "CRAZYがより良い会社になるために、改善してほしい点や、こんなことがあったら嬉しいという要望があれば教えてください。",
    "placeholder": "率直なご意見をお聞かせください..."
  }
] 